README.txt
setup.py
lib/DLNetSNMP/DLNetSNMP.py
lib/DLNetSNMP/DLNetSNMP_CONSTANTS.py
lib/DLNetSNMP/Singleton.py
lib/DLNetSNMP/__init__.py
lib/DLNetSNMP.egg-info/PKG-INFO
lib/DLNetSNMP.egg-info/SOURCES.txt
lib/DLNetSNMP.egg-info/dependency_links.txt
lib/DLNetSNMP.egg-info/not-zip-safe
lib/DLNetSNMP.egg-info/top_level.txt
