Metadata-Version: 1.0
Name: DLNetSNMP
Version: 0.4.1
Summary: A small but complete NetSNMP ctypes wrapper.
Home-page: http://www.dlevel.com/products/opensource/dlnetsnmp
Author: Alessandro Iob
Author-email: alessandro.iob@dlevel.com
License: GPL
Keywords: snmp dlevel dlnetsnmp
Platform: UNKNOWN
Classifier: Development Status :: 4 - Beta
Classifier: Environment :: Console
Classifier: Intended Audience :: Developers
Classifier: Programming Language :: Python
Classifier: License :: OSI Approved :: GNU General Public License (GPL)
Classifier: Topic :: Internet
Classifier: Operating System :: POSIX
Classifier: Operating System :: MacOS :: MacOS X
Classifier: Operating System :: Microsoft :: Windows :: Windows NT/2000
